{
  "days_alive": 13,
  "total_experience": 56,
  "current_stage": "EGG",
  "health_state": "CRITICAL",
  "days_since_last_commit": 12,
  "days_in_current_stage": 13,
  "stage_stability": 0,
  "evolution_history": [],
  "last_update": "2025-09-06",
  "is_first_run": false,
  "best_streak": 1,
  "total_commits": 262,
  "stage_days": {
    "EGG": 13,
    "HATCHLING": 0,
    "YOUNG": 0,
    "ADULT": 0,
    "LEGENDARY": 0
  },
  "achievements": [],
  "devolution_warnings": 9,
  "last_commit_date": "2025-08-25",
  "consecutive_inactive_days": 3
}